obsidian_sticky_notes/__init__.py
obsidian_sticky_notes/app.py
obsidian_sticky_notes/renderer.py
obsidian_sticky_notes/assets/css/sticky.css
obsidian_sticky_notes/assets/js/boot.js
obsidian_sticky_notes-1.7.0.dist-info/METADATA
obsidian_sticky_notes-1.7.0.dist-info/WHEEL
obsidian_sticky_notes-1.7.0.dist-info/entry_points.txt
obsidian_sticky_notes-1.7.0.dist-info/top_level.txt
obsidian_sticky_notes-1.7.0.dist-info/RECORD
