Metadata-Version: 2.4
Name: obsidian-sticky-notes
Version: 1.7.0
Summary: GTK/WebKit sticky notes that render the Obsidian Markdown file on Linux.
Author-email: Gustavo Papi <gusbemacbe@gmail.com>
Maintainer-email: Gustavo Papi <gusbemacbe@gmail.com>
Requires-Python: >=3.10
Requires-Dist: markdown-it-py>=3.0.0
Requires-Dist: mdit-py-plugins>=0.3.0
Requires-Dist: pygobject>=3.46.0
Requires-Dist: python-frontmatter>=1.0.1
Requires-Dist: PyYAML>=6.0
Requires-Dist: watchdog>=4.0.0
